{
  "resourceType": "OperationDefinition",
  "id": "$sqlquery-run",
  "url": "http://sql-on-fhir.org/OperationDefinition/$sqlquery-run",
  "version": "0.0.1",
  "name": "$sqlquery-run",
  "code": "sqlquery-run",
  "status": "active",
  "kind": "operation",
  "description": "Execute a SQLQuery Library against ViewDefinition tables.",
  "system": true,
  "type": true,
  "instance": true,
  "resource": ["Library"],
  "parameter": [
    {
      "name": "_format",
      "use": "in",
      "min": 1,
      "max": "1",
      "type": "code",
      "documentation": "Output format for the result (json, ndjson, csv, parquet, fhir). Use fhir to return results as a FHIR Parameters resource.",
      "binding": {
        "strength": "extensible",
        "valueSet": "http://sql-on-fhir.org/ValueSet/output-format"
      }
    },
    {
      "name": "header",
      "use": "in",
      "min": 0,
      "max": "1",
      "type": "boolean",
      "documentation": "Include CSV headers (default true). Applies only when csv output is requested."
    },
    {
      "name": "queryReference",
      "use": "in",
      "min": 0,
      "max": "1",
      "type": "Reference",
      "documentation": "Reference to a SQLQuery Library stored on the server."
    },
    {
      "name": "queryResource",
      "use": "in",
      "min": 0,
      "max": "1",
      "type": "Resource",
      "extension": [
        {
          "url": "http://hl7.org/fhir/StructureDefinition/operationdefinition-allowed-type",
          "valueUri": "https://sql-on-fhir.org/ig/StructureDefinition/SQLQuery"
        }
      ],
      "documentation": "Inline SQLQuery Library resource to execute."
    },
    {
      "name": "parameters",
      "use": "in",
      "min": 0,
      "max": "1",
      "type": "Parameters",
      "documentation": "Input parameters for the query. Parameters are bound by name to parameters declared in the SQLQuery Library (Library.parameter.name). Parameter types are mapped using the appropriate value[x] type matching the declared parameter type."
    },
    {
      "name": "source",
      "use": "in",
      "min": 0,
      "max": "1",
      "type": "string",
      "documentation": "External data source containing the ViewDefinition tables."
    },
    {
      "name": "return",
      "use": "out",
      "min": 1,
      "max": "1",
      "type": "Resource",
      "extension": [
        {
          "url": "http://hl7.org/fhir/StructureDefinition/operationdefinition-allowed-type",
          "valueUri": "Binary"
        },
        {
          "url": "http://hl7.org/fhir/StructureDefinition/operationdefinition-allowed-type",
          "valueUri": "Parameters"
        }
      ],
      "documentation": "Query results. Returns Binary for flat formats (csv, json, ndjson, parquet) or Parameters for _format=fhir."
    }
  ]
}
